scikit_learn-stubs/README.md
scikit_learn-stubs/__check_build/__init__.pyi
scikit_learn-stubs/__check_build/_check_build.pyi
scikit_learn-stubs/__init__.pyi
scikit_learn-stubs/_build_utils/__init__.pyi
scikit_learn-stubs/_build_utils/openmp_helpers.pyi
scikit_learn-stubs/_build_utils/pre_build_helpers.pyi
scikit_learn-stubs/_config.pyi
scikit_learn-stubs/_distributor_init.pyi
scikit_learn-stubs/_loss/__init__.pyi
scikit_learn-stubs/_loss/_loss.pyi
scikit_learn-stubs/_loss/glm_distribution.pyi
scikit_learn-stubs/_loss/link.pyi
scikit_learn-stubs/_loss/loss.pyi
scikit_learn-stubs/_min_dependencies.pyi
scikit_learn-stubs/_typing.pyi
scikit_learn-stubs/base.pyi
scikit_learn-stubs/calibration.pyi
scikit_learn-stubs/cluster/__init__.pyi
scikit_learn-stubs/cluster/_affinity_propagation.pyi
scikit_learn-stubs/cluster/_agglomerative.pyi
scikit_learn-stubs/cluster/_bicluster.pyi
scikit_learn-stubs/cluster/_birch.pyi
scikit_learn-stubs/cluster/_bisect_k_means.pyi
scikit_learn-stubs/cluster/_dbscan.pyi
scikit_learn-stubs/cluster/_dbscan_inner.pyi
scikit_learn-stubs/cluster/_feature_agglomeration.pyi
scikit_learn-stubs/cluster/_k_means_common.pyi
scikit_learn-stubs/cluster/_k_means_elkan.pyi
scikit_learn-stubs/cluster/_k_means_lloyd.pyi
scikit_learn-stubs/cluster/_kmeans.pyi
scikit_learn-stubs/cluster/_mean_shift.pyi
scikit_learn-stubs/cluster/_optics.pyi
scikit_learn-stubs/cluster/_spectral.pyi
scikit_learn-stubs/compose/__init__.pyi
scikit_learn-stubs/compose/_column_transformer.pyi
scikit_learn-stubs/compose/_target.pyi
scikit_learn-stubs/conftest.pyi
scikit_learn-stubs/covariance/__init__.pyi
scikit_learn-stubs/covariance/_elliptic_envelope.pyi
scikit_learn-stubs/covariance/_empirical_covariance.pyi
scikit_learn-stubs/covariance/_graph_lasso.pyi
scikit_learn-stubs/covariance/_robust_covariance.pyi
scikit_learn-stubs/covariance/_shrunk_covariance.pyi
scikit_learn-stubs/cross_decomposition/__init__.pyi
scikit_learn-stubs/cross_decomposition/_pls.pyi
scikit_learn_stubs-0.0.2.dist-info/WHEEL
scikit_learn_stubs-0.0.2.dist-info/METADATA
scikit_learn_stubs-0.0.2.dist-info/RECORD
