Metadata-Version: 2.3
Name: scikit-learn-stubs
Version: 0.0.2
Summary: scikit-learn stubs from the Microsoft python-type-stubs repository
Keywords: scikit-learn,sklearn,stubs
Author: Bagard Hoel
License: MIT
Classifier: License :: OSI Approved :: MIT License
Classifier: Programming Language :: Python
Classifier: Programming Language :: Python :: 3.9
Classifier: Programming Language :: Python :: 3.10
Classifier: Programming Language :: Python :: 3.11
Classifier: Programming Language :: Python :: 3.12
Classifier: Programming Language :: Python :: 3.13
Classifier: Programming Language :: Python :: Implementation :: CPython
Classifier: Operating System :: OS Independent
Classifier: Intended Audience :: Developers
Requires-Python: >=3.9
Project-URL: Bug Tracker, https://github.com/hoel-bagard/scikit-learn-stubs/issues
Project-URL: Homepage, https://github.com/hoel-bagard/scikit-learn-stubs
